{
  "sections": {
    "main": {
      "type": "main-page",
      "settings": {
      }
    },
    "1628277772b4d0b726": {
      "type": "collage",
      "blocks": {
        "1628277772b4d0b726-0": {
          "type": "video",
          "settings": {
            "cover_image": "shopify:\/\/shop_images\/Untitled_design_-_2020-05-16T001455.638.png",
            "video_url": "https:\/\/youtu.be\/8NGM5e-60H8",
            "description": "Describe the video for customers using screen readers",
            "image_padding": false
          }
        },
        "1628277772b4d0b726-1": {
          "type": "product",
          "settings": {
            "product": "",
            "secondary_background": false,
            "second_image": false,
            "image_padding": false
          }
        },
        "1628277772b4d0b726-2": {
          "type": "collection",
          "settings": {
            "collection": "",
            "image_padding": false,
            "color_scheme": "background-1"
          }
        }
      },
      "block_order": [
        "1628277772b4d0b726-0",
        "1628277772b4d0b726-1",
        "1628277772b4d0b726-2"
      ],
      "settings": {
        "heading": "Multimedia collage",
        "desktop_layout": "left",
        "mobile_layout": "collage"
      }
    }
  },
  "order": [
    "main",
    "1628277772b4d0b726"
  ]
}
